LICENSE
README.md
setup.py
abork_logger.egg-info/PKG-INFO
abork_logger.egg-info/SOURCES.txt
abork_logger.egg-info/dependency_links.txt
abork_logger.egg-info/requires.txt
abork_logger.egg-info/top_level.txt
logger/__init__.py
logger/module.py