Metadata-Version: 2.1
Name: abork-logger
Version: 1.0.6
Summary: Logging Library
Author: Alex Bork
License-File: LICENSE
